default_pickling/__init__.py
default_pickling/default_pickling.py
default_pickling-0.3.dist-info/LICENSE
default_pickling-0.3.dist-info/METADATA
default_pickling-0.3.dist-info/WHEEL
default_pickling-0.3.dist-info/top_level.txt
default_pickling-0.3.dist-info/RECORD
